{
  "version": "0.1",
  "prefixes": {
    "ext": "http://mu.semte.ch/vocabularies/ext/"
  },
  "resources": {
    "redirects": {
      "class": "ext:Intent",
      "attributes": {
        "intent": {
          "type": "string",
          "predicate": "ext:intentName"
        },
        "redirect-url": {
          "type": "uri-set",
          "predicate": "ext:redirectUrls"
        }
      },
      "relationships": {},
      "new-resource-base": "http://data.yourdomain.info/intents/"
    }
  }
}
